aind_dynamic_foraging_multisession_analysis/__init__.py
aind_dynamic_foraging_multisession_analysis/multisession_load.py
aind_dynamic_foraging_multisession_analysis/multisession_plot.py
aind_dynamic_foraging_multisession_analysis-0.0.18.dist-info/licenses/LICENSE
aind_dynamic_foraging_multisession_analysis-0.0.18.dist-info/METADATA
aind_dynamic_foraging_multisession_analysis-0.0.18.dist-info/WHEEL
aind_dynamic_foraging_multisession_analysis-0.0.18.dist-info/top_level.txt
aind_dynamic_foraging_multisession_analysis-0.0.18.dist-info/RECORD
